ziaplot/__init__.py
ziaplot/calcs.py
ziaplot/canvas.py
ziaplot/config.py
ziaplot/container.py
ziaplot/diagram_stack.py
ziaplot/drawable.py
ziaplot/element.py
ziaplot/layout.py
ziaplot/text.py
ziaplot/util.py
ziaplot/annotations/__init__.py
ziaplot/annotations/annotations.py
ziaplot/annotations/text.py
ziaplot/charts/__init__.py
ziaplot/charts/bar.py
ziaplot/charts/pie.py
ziaplot/diagrams/__init__.py
ziaplot/diagrams/diagram.py
ziaplot/diagrams/graph.py
ziaplot/diagrams/graphlog.py
ziaplot/diagrams/oned.py
ziaplot/diagrams/polar.py
ziaplot/diagrams/smith.py
ziaplot/diagrams/smithgrid.py
ziaplot/diagrams/ticker.py
ziaplot/discrete/__init__.py
ziaplot/discrete/bars.py
ziaplot/discrete/contour.py
ziaplot/discrete/polar.py
ziaplot/discrete/polylines.py
ziaplot/geo/__init__.py
ziaplot/geo/bezier.py
ziaplot/geo/function.py
ziaplot/geo/implicit.py
ziaplot/geo/integral.py
ziaplot/geo/line.py
ziaplot/geo/point.py
ziaplot/geo/tangents.py
ziaplot/shapes/__init__.py
ziaplot/shapes/polygon.py
ziaplot/shapes/shapes.py
ziaplot/style/__init__.py
ziaplot/style/colors.py
ziaplot/style/css.py
ziaplot/style/style.py
ziaplot/style/themes.py
ziaplot-0.8.dist-info/LICENSE.txt
ziaplot-0.8.dist-info/METADATA
ziaplot-0.8.dist-info/WHEEL
ziaplot-0.8.dist-info/top_level.txt
ziaplot-0.8.dist-info/RECORD
